{
  "headlines": [
    {
      "title": "USD/MXN Edges Higher as Middle East Risk Lingers - DailyForex",
      "source": "Google News",
      "label": "bullish",
      "score": 0.8524,
      "currencies": [
        "USD"
      ]
    },
    {
      "title": "GlobalPay Launches Forex Card Partner Platform - IBS Intelligence",
      "source": "Google News",
      "label": "neutral",
      "score": 0.0,
      "currencies": []
    },
    {
      "title": "Aurra Markets Named 'Top Low Spread Forex Broker 2026' at Money Expo Abu Dhabi - Yahoo Finance",
      "source": "Google News",
      "label": "bullish",
      "score": 0.6655,
      "currencies": []
    },
    {
      "title": "South Korea to ease won access, aims for freely convertible currency - investingLive",
      "source": "Google News",
      "label": "bullish",
      "score": 0.6147,
      "currencies": []
    },
    {
      "title": "AUD Rises as Rate Gap Offsets Yen Intervention Fears - TradingPedia",
      "source": "Google News",
      "label": "bullish",
      "score": 0.4983,
      "currencies": [
        "AUD"
      ]
    },
    {
      "title": "Traveling Abroad? Order Currency Before You Go - NerdWallet",
      "source": "Google News",
      "label": "neutral",
      "score": 0.0,
      "currencies": []
    },
    {
      "title": "South Korea to ease forex rules for foreigners to trade won in push to liberalise market - The Business Times",
      "source": "Google News",
      "label": "bullish",
      "score": 0.5672,
      "currencies": []
    },
    {
      "title": "Forex Today: Oil prices rise further, keeping markets on edge - FXStreet",
      "source": "Google News",
      "label": "bullish",
      "score": 0.8349,
      "currencies": []
    },
    {
      "title": "exchange rate - Encyclopedia Britannica",
      "source": "Google News",
      "label": "neutral",
      "score": 0.0,
      "currencies": []
    },
    {
      "title": "AFRICA-FX-Kenyan currency could be boosted by remittances - Reuters",
      "source": "Google News",
      "label": "bullish",
      "score": 0.925,
      "currencies": []
    },
    {
      "title": "India\u2019s Forex reserves reach record high of over 728 billion USD - Newsonair",
      "source": "Google News",
      "label": "bullish",
      "score": 0.8971,
      "currencies": [
        "USD"
      ]
    },
    {
      "title": "15 Best Forex Pairs to Trade - TMGM trading",
      "source": "Google News",
      "label": "neutral",
      "score": 0.0,
      "currencies": []
    },
    {
      "title": "RBC turns bullish on Atalaya Mining as Touro permit outlook brightens",
      "source": "Investing.com",
      "label": "bullish",
      "score": 0.8612,
      "currencies": []
    },
    {
      "title": "H.C. Wainwright reiterates Harmony Biosciences stock rating on demand beat",
      "source": "Investing.com",
      "label": "neutral",
      "score": 0.0,
      "currencies": []
    },
    {
      "title": "BTQ partners with TIDAL PWR on quantum data center architecture",
      "source": "Investing.com",
      "label": "bullish",
      "score": 0.5003,
      "currencies": []
    },
    {
      "title": "BrainsWay invests $3 million in Radial Health network",
      "source": "Investing.com",
      "label": "neutral",
      "score": 0.0,
      "currencies": []
    },
    {
      "title": "Standard BioTools files merger registration with Treeline",
      "source": "Investing.com",
      "label": "neutral",
      "score": 0.0,
      "currencies": []
    },
    {
      "title": "Trevi Therapeutics stock price target raised to $24 by H.C. Wainwright",
      "source": "Investing.com",
      "label": "bullish",
      "score": 0.8204,
      "currencies": []
    },
    {
      "title": "Anduril and Archer unveil hybrid-electric VTOL aircraft platform",
      "source": "Investing.com",
      "label": "neutral",
      "score": 0.0,
      "currencies": []
    },
    {
      "title": "Immunome doses first patient in IM-3050 cancer therapy trial",
      "source": "Investing.com",
      "label": "neutral",
      "score": 0.0,
      "currencies": []
    }
  ],
  "run_id": 1
}