{
  "headlines": [
    {
      "title": "After currency headwinds, Israeli tech welcomes a forex rebound (WIX:NASDAQ) - Seeking Alpha",
      "source": "Google News",
      "label": "bullish",
      "score": 0.9451,
      "currencies": []
    },
    {
      "title": "EUR/USD Signal: Hits Lower Side of Bearish Flag Ahead of ECB Decision - DailyForex",
      "source": "Google News",
      "label": "bearish",
      "score": -0.6758,
      "currencies": [
        "EUR",
        "USD"
      ]
    },
    {
      "title": "Vice Minister Huh Urges Exporters to Convert Currency as Forex Eases - \uc870\uc120\uc77c\ubcf4",
      "source": "Google News",
      "label": "neutral",
      "score": 0.0,
      "currencies": []
    },
    {
      "title": "Japan ready to take decisive currency action as yen hits 40-year low - Reuters",
      "source": "Google News",
      "label": "neutral",
      "score": 0.0,
      "currencies": []
    },
    {
      "title": "Yen Hits Fresh 40-Year Low. Can Japan Still Defend Its Currency? - ActionForex",
      "source": "Google News",
      "label": "neutral",
      "score": 0.0,
      "currencies": []
    },
    {
      "title": "USD/MXN Forecast: Mexican peso stays neutral as uncertainty persists - FOREX.com",
      "source": "Google News",
      "label": "neutral",
      "score": 0.0,
      "currencies": [
        "USD"
      ]
    },
    {
      "title": "Yen Hovers Near Multi-Decade Low on Intervention - TradingPedia",
      "source": "Google News",
      "label": "bearish",
      "score": -0.8778,
      "currencies": []
    },
    {
      "title": "Large currency options set to expire Wednesday - Investing.com",
      "source": "Google News",
      "label": "neutral",
      "score": 0.0,
      "currencies": []
    },
    {
      "title": "Forex Forecasts \u2013 US Dollar Defends Key 50-Day EMA Across Major Pairs - Yahoo Finance",
      "source": "Google News",
      "label": "bullish",
      "score": 0.6216,
      "currencies": []
    },
    {
      "title": "South Korea to ease forex rules for foreigners to trade won in push to liberalise market - The Business Times",
      "source": "Google News",
      "label": "bullish",
      "score": 0.5672,
      "currencies": []
    },
    {
      "title": "15 Best Forex Pairs to Trade - TMGM trading",
      "source": "Google News",
      "label": "neutral",
      "score": 0.0,
      "currencies": []
    },
    {
      "title": "Japan ready to take decisive action on forex if needed, finance minister says - The Standard (HK)",
      "source": "Google News",
      "label": "bullish",
      "score": 0.5701,
      "currencies": []
    },
    {
      "title": "Form 4 Rivian Automotive Inc For: 22 July",
      "source": "Investing.com",
      "label": "neutral",
      "score": 0.0,
      "currencies": []
    },
    {
      "title": "Form 4 AvalonBay Communities Inc For: 22 July",
      "source": "Investing.com",
      "label": "neutral",
      "score": 0.0,
      "currencies": []
    },
    {
      "title": "Chemung earnings beat by $0.05, revenue topped estimates",
      "source": "Investing.com",
      "label": "bullish",
      "score": 0.9457,
      "currencies": []
    },
    {
      "title": "Kalanick\u2019s Atoms raises $1.7B in a16z-led round for industrial AI",
      "source": "Investing.com",
      "label": "bullish",
      "score": 0.864,
      "currencies": []
    },
    {
      "title": "Graco shares rise on earnings beat despite revenue miss",
      "source": "Investing.com",
      "label": "bullish",
      "score": 0.8312,
      "currencies": []
    },
    {
      "title": "Google beats quarterly revenue expectations off of enterprise AI surge",
      "source": "Investing.com",
      "label": "bullish",
      "score": 0.91,
      "currencies": []
    },
    {
      "title": "Goosehead Insurance earnings beat by $0.16, revenue topped estimates",
      "source": "Investing.com",
      "label": "bullish",
      "score": 0.941,
      "currencies": []
    },
    {
      "title": "Sigma Lithium faces $540,000 in fines from Brazil regulator",
      "source": "Investing.com",
      "label": "bearish",
      "score": -0.9558,
      "currencies": []
    }
  ],
  "run_id": 1
}